README.txt
TODO
setup.cfg
setup.py
w20e/__init__.py
w20e.forms.egg-info/PKG-INFO
w20e.forms.egg-info/SOURCES.txt
w20e.forms.egg-info/dependency_links.txt
w20e.forms.egg-info/entry_points.txt
w20e.forms.egg-info/not-zip-safe
w20e.forms.egg-info/requires.txt
w20e.forms.egg-info/top_level.txt
w20e/forms/CHANGES
w20e/forms/__init__.py
w20e/forms/config.py
w20e/forms/configure.zcml
w20e/forms/exceptions.py
w20e/forms/form.py
w20e/forms/formdata.py
w20e/forms/formmodel.py
w20e/forms/formview.py
w20e/forms/interfaces.py
w20e/forms/meta.zcml
w20e/forms/metadirectives.py
w20e/forms/registry.py
w20e/forms/utils.py
w20e/forms/version.txt
w20e/forms/data/__init__.py
w20e/forms/data/field.py
w20e/forms/model/__init__.py
w20e/forms/model/converters.py
w20e/forms/model/fieldproperties.py
w20e/forms/model/validators.py
w20e/forms/plone/README.txt
w20e/forms/plone/__init__.py
w20e/forms/plone/file.py
w20e/forms/plone/form.pt
w20e/forms/plone/form.py
w20e/forms/plone/archetypes/ajaxvalidator.py
w20e/forms/plone/archetypes/atctbaseobject.py
w20e/forms/plone/archetypes/view.pt
w20e/forms/plone/archetypes/view.py
w20e/forms/pyramid/README.txt
w20e/forms/pyramid/__init__.py
w20e/forms/pyramid/file.py
w20e/forms/pyramid/formview.py
w20e/forms/pyramid/vocab.py
w20e/forms/rendering/__init__.py
w20e/forms/rendering/baserenderer.py
w20e/forms/rendering/control.py
w20e/forms/rendering/controlgroup.py
w20e/forms/rendering/group.py
w20e/forms/rendering/interfaces.py
w20e/forms/rendering/renderables.py
w20e/forms/rendering/html/__init__.py
w20e/forms/rendering/html/cancel.py
w20e/forms/rendering/html/cardgroup.py
w20e/forms/rendering/html/checkbox.py
w20e/forms/rendering/html/file.py
w20e/forms/rendering/html/flowgroup.py
w20e/forms/rendering/html/hidden.py
w20e/forms/rendering/html/input.py
w20e/forms/rendering/html/password.py
w20e/forms/rendering/html/renderer.py
w20e/forms/rendering/html/reset.py
w20e/forms/rendering/html/richtext.py
w20e/forms/rendering/html/select.py
w20e/forms/rendering/html/stepgroup.py
w20e/forms/rendering/html/submit.py
w20e/forms/rendering/html/templates.py
w20e/forms/rendering/html/text.py
w20e/forms/rendering/html/templates/cancel.pt
w20e/forms/rendering/html/templates/cardgroup.pt
