Metadata-Version: 1.1
Name: w20e.forms
Version: 1.0.2b
Summary: Python API for creating and handling forms
Home-page: UNKNOWN
Author: D.A.Dokter
Author-email: dokter@w20e.com
License: GPL
Keywords: forms
Platform: UNKNOWN
Classifier: Development Status :: 4 - Beta
Classifier: Framework :: Plone
Classifier: Framework :: Pylons
Classifier: Intended Audience :: Developers
Classifier: License :: OSI Approved :: GNU General Public License (GPL)
Classifier: Operating System :: OS Independent
Classifier: Programming Language :: Python
